aiohttp/payload_streamer.py
aiohttp/streams.py
aiohttp/_http_parser.cpython-37m-aarch64-linux-gnu.so
aiohttp/web_protocol.py
aiohttp/tracing.py
aiohttp/typedefs.py
aiohttp/_frozenlist.cpython-37m-aarch64-linux-gnu.so
aiohttp/web_middlewares.py
aiohttp/client.py
aiohttp/signals.py
aiohttp/locks.py
aiohttp/_http_parser.pyx
aiohttp/web_exceptions.py
aiohttp/cookiejar.py
aiohttp/__init__.py
aiohttp/multipart.py
aiohttp/_headers.pxi
aiohttp/client_reqrep.py
aiohttp/_find_header.pxd
aiohttp/web_fileresponse.py
aiohttp/client_ws.py
aiohttp/web_app.py
aiohttp/helpers.py
aiohttp/_find_header.c
aiohttp/_helpers.c
aiohttp/_helpers.cpython-37m-aarch64-linux-gnu.so
aiohttp/_helpers.pyx
aiohttp/web_log.py
aiohttp/_websocket.cpython-37m-aarch64-linux-gnu.so
aiohttp/_http_writer.c
aiohttp/client_exceptions.py
aiohttp/log.py
aiohttp/resolver.py
aiohttp/web_request.py
aiohttp/web_routedef.py
aiohttp/connector.py
aiohttp/test_utils.py
aiohttp/_frozenlist.c
aiohttp/py.typed
aiohttp/_cparser.pxd
aiohttp/_http_writer.cpython-37m-aarch64-linux-gnu.so
aiohttp/web_response.py
aiohttp/_find_header.h
aiohttp/_frozenlist.pyx
aiohttp/frozenlist.pyi
aiohttp/web_server.py
aiohttp/http.py
aiohttp/web.py
aiohttp/_http_parser.c
aiohttp/http_exceptions.py
aiohttp/abc.py
aiohttp/http_parser.py
aiohttp/http_websocket.py
aiohttp/web_runner.py
aiohttp/formdata.py
aiohttp/_helpers.pyi
aiohttp/worker.py
aiohttp/hdrs.py
aiohttp/web_urldispatcher.py
aiohttp/_websocket.c
aiohttp/client_proto.py
aiohttp/payload.py
aiohttp/web_ws.py
aiohttp/_http_writer.pyx
aiohttp/http_writer.py
aiohttp/pytest_plugin.py
aiohttp/base_protocol.py
aiohttp/tcp_helpers.py
aiohttp/signals.pyi
aiohttp/frozenlist.py
aiohttp/_websocket.pyx
aiohttp/.hash/_helpers.pyi.hash
aiohttp/.hash/_http_writer.pyx.hash
aiohttp/.hash/_helpers.pyx.hash
aiohttp/.hash/_frozenlist.pyx.hash
aiohttp/.hash/_cparser.pxd.hash
aiohttp/.hash/_find_header.pxd.hash
aiohttp_edit-3.7.4.post11.dist-info/METADATA
aiohttp_edit-3.7.4.post11.dist-info/top_level.txt
aiohttp_edit-3.7.4.post11.dist-info/RECORD
aiohttp_edit-3.7.4.post11.dist-info/LICENSE.txt
aiohttp_edit-3.7.4.post11.dist-info/WHEEL
