Metadata-Version: 2.1
Name: aiohttp-edit
Version: 3.7.4.post11
Summary: Async http client/server framework (asyncio)
Home-page: https://github.com/aio-libs/aiohttp
Author: Nikolay Kim
Author-email: fafhrd91@gmail.com
Maintainer: Nikolay Kim <fafhrd91@gmail.com>, Andrew Svetlov <andrew.svetlov@gmail.com>
Maintainer-email: aio-libs@googlegroups.com
License: Apache 2
Project-URL: Chat: Gitter, https://gitter.im/aio-libs/Lobby
Project-URL: CI: Azure Pipelines, https://dev.azure.com/aio-libs/aiohttp/_build
Project-URL: Coverage: codecov, https://codecov.io/github/aio-libs/aiohttp
Project-URL: Docs: RTD, https://docs.aiohttp.org
Project-URL: GitHub: issues, https://github.com/aio-libs/aiohttp/issues
Project-URL: GitHub: repo, https://github.com/aio-libs/aiohttp
Platform: UNKNOWN
Classifier: License :: OSI Approved :: Apache Software License
Classifier: Intended Audience :: Developers
Classifier: Programming Language :: Python
Classifier: Programming Language :: Python :: 3
Classifier: Programming Language :: Python :: 3.6
Classifier: Programming Language :: Python :: 3.7
Classifier: Programming Language :: Python :: 3.8
Classifier: Programming Language :: Python :: 3.9
Classifier: Development Status :: 5 - Production/Stable
Classifier: Operating System :: POSIX
Classifier: Operating System :: MacOS :: MacOS X
Classifier: Operating System :: Microsoft :: Windows
Classifier: Topic :: Internet :: WWW/HTTP
Classifier: Framework :: AsyncIO
Requires-Python: >=3.6
Provides-Extra: speedups
